{
    "direc": [
        {
            "id": 1,
	    "calle": "muñoz gamero 1211",
	    "comuna": "Recoleta",
            "userId": 1
        },
        {
            "id": 2,
	    "calle": "Av. Independencia 4991",
	    "comuna": "Independencia",
            "userId": 1
        },
	{
            "id": 3,
	    "calle": "Cartagena 2354",
	    "comuna": "Cartagena",
            "userId": 2
        },
        {
            "id": 4,
	    "calle": "Holanda 4310",
	    "comuna": "Nuñoa",
            "userId": 2
        }
    ],
}
